django_perf_rec/__init__.py
django_perf_rec/api.py
django_perf_rec/cache.py
django_perf_rec/db.py
django_perf_rec/operation.py
django_perf_rec/py.typed
django_perf_rec/pytest_plugin.py
django_perf_rec/settings.py
django_perf_rec/sql.py
django_perf_rec/types.py
django_perf_rec/utils.py
django_perf_rec/yaml.py
django_perf_rec-4.31.0.dist-info/licenses/LICENSE
django_perf_rec-4.31.0.dist-info/METADATA
django_perf_rec-4.31.0.dist-info/WHEEL
django_perf_rec-4.31.0.dist-info/entry_points.txt
django_perf_rec-4.31.0.dist-info/top_level.txt
django_perf_rec-4.31.0.dist-info/RECORD
