Metadata-Version: 2.4
Name: django-perf-rec
Version: 4.31.0
Summary: Keep detailed records of the performance of your Django code.
Author-email: Adam Johnson <me@adamj.eu>
License-Expression: MIT
Project-URL: Changelog, https://github.com/adamchainz/django-perf-rec/blob/main/CHANGELOG.rst
Project-URL: Funding, https://adamj.eu/books/
Project-URL: Repository, https://github.com/adamchainz/django-perf-rec
Keywords: Django
Classifier: Development Status :: 6 - Mature
Classifier: Framework :: Django :: 4.2
Classifier: Framework :: Django :: 5.0
Classifier: Framework :: Django :: 5.1
Classifier: Framework :: Django :: 5.2
Classifier: Framework :: Django :: 6.0
Classifier: Intended Audience :: Developers
Classifier: Natural Language :: English
Classifier: Operating System :: OS Independent
Classifier: Programming Language :: Python :: 3 :: Only
Classifier: Programming Language :: Python :: 3.9
Classifier: Programming Language :: Python :: 3.10
Classifier: Programming Language :: Python :: 3.11
Classifier: Programming Language :: Python :: 3.12
Classifier: Programming Language :: Python :: 3.13
Classifier: Programming Language :: Python :: 3.14
Classifier: Programming Language :: Python :: Implementation :: CPython
Classifier: Typing :: Typed
Requires-Python: >=3.9
License-File: LICENSE
Requires-Dist: django>=4.2
Requires-Dist: pyyaml
Requires-Dist: sqlparse>=0.4.4
Dynamic: license-file
